oasis_api/__init__.py
oasis_api/api.py
oasis_api-3.0.2.dist-info/licenses/LICENSE
oasis_api-3.0.2.dist-info/METADATA
oasis_api-3.0.2.dist-info/WHEEL
oasis_api-3.0.2.dist-info/top_level.txt
oasis_api-3.0.2.dist-info/RECORD
