Metadata-Version: 2.4
Name: oasis-api
Version: 3.0.2
Summary: Python API for the Open Acquisition System for IEPE Sensors (OASIS)
Author-email: Johannes Maierhofer <j.maierhofer@tum.de>, Oliver Zobel <oliver.zobel@tum.de>
Project-URL: Homepage, https://gitlab.com/oasis-acquisition/oasis-api
Classifier: Development Status :: 4 - Beta
Classifier: Intended Audience :: Science/Research
Classifier: Intended Audience :: Developers
Classifier: License :: OSI Approved :: MIT License
Classifier: Operating System :: OS Independent
Classifier: Programming Language :: Python :: 3
Classifier: Programming Language :: Python :: 3.11
Classifier: Programming Language :: Python :: 3.12
Classifier: Topic :: Scientific/Engineering
Requires-Python: >=3.11
License-File: LICENSE
Requires-Dist: pyserial
Requires-Dist: numpy
Requires-Dist: h5py
Requires-Dist: matplotlib
Dynamic: license-file
